{
    "id": "bundle--c13f590d-f0fd-43aa-b061-87d4b9082046",
    "objects": [
        {
            "country": "GE",
            "created": "2021-03-13T20:09:20.991706Z",
            "created_by_ref": "identity--8ce3f695-d5a4-4dc8-9e93-a65af453a31a",
            "id": "location--42fa4b37-383c-47fc-bc82-061f7c1533b4",
            "modified": "2021-12-01T16:19:51.601791Z",
            "name": "Georgia",
            "spec_version": "2.1",
            "type": "location"
        }
    ],
    "type": "bundle"
}