{
    "id": "bundle--ad687c2c-7822-4fed-bceb-d40e4fd9db35",
    "objects": [
        {
            "country": "VE",
            "created": "2021-03-13T20:09:21.170582Z",
            "created_by_ref": "identity--8ce3f695-d5a4-4dc8-9e93-a65af453a31a",
            "id": "location--463acaa8-65da-4d50-8090-08883bf31ad5",
            "modified": "2021-12-01T16:19:51.601791Z",
            "name": "Venezuela, Bolivarian Republic of",
            "spec_version": "2.1",
            "type": "location"
        }
    ],
    "type": "bundle"
}